musicftdl/__init__.py
musicftdl/cli.py
musicftdl/id3_genres.py
musicftdl/models.py
musicftdl/musicftdl.py
musicftdl/utils.py
musicftdl-0.1.1.dist-info/AUTHORS.rst
musicftdl-0.1.1.dist-info/LICENSE
musicftdl-0.1.1.dist-info/METADATA
musicftdl-0.1.1.dist-info/WHEEL
musicftdl-0.1.1.dist-info/entry_points.txt
musicftdl-0.1.1.dist-info/top_level.txt
musicftdl-0.1.1.dist-info/RECORD
