Metadata-Version: 2.1
Name: musicftdl
Version: 0.1.1
Summary: A CLI tool to download music of Jay Chou and other singers with full song tags.
Home-page: https://github.com/lonsty/musicftdl
Author: Allen Shaw
Author-email: lonsty@sina.com
License: MIT license
Keywords: musicftdl
Platform: UNKNOWN
Classifier: Development Status :: 2 - Pre-Alpha
Classifier: Intended Audience :: Developers
Classifier: License :: OSI Approved :: MIT License
Classifier: Natural Language :: English
Classifier: Programming Language :: Python :: 3
Classifier: Programming Language :: Python :: 3.6
Classifier: Programming Language :: Python :: 3.7
Classifier: Programming Language :: Python :: 3.8
Requires-Python: >=3.6
Requires-Dist: Click (>=7.0)
Requires-Dist: eyeD3 (>=0.9.5)
Requires-Dist: pydantic (>=1.5.1)
Requires-Dist: requests (>=2.23.0)
Requires-Dist: prettytable (>=2.0.0)
Requires-Dist: python-dateutil (>=2.8.1)
